Workbook

Sheet 00-管理看板
A1: 应收账款管理工具包
A2: 模拟企业：华辰智能设备有限公司。看板数字来自应收明细，黄色区域为人工维护。
A5: 指标 | B5: 本期结果 | C5: 管理阈值 | D5: 主管动作
A6: 应收余额 | B6: =SUM('02-应收明细'!J6:J20) -> 23617000 | C6: 结合收入 | D6: 解释余额变化
A7: 逾期余额 | B7: =SUMIF('02-应收明细'!P6:P20,"逾期",'02-应收明细'!J6:J20) -> 10509000 | C7: 逐笔 | D7: 形成Owner和行动
A8: 逾期率 | B8: =IF(B6=0,0,B7/B6) -> 0.44497608 | C8: 0.15 | D8: 超过阈值专项分析
A9: 90天以上逾期 | B9: =SUMIF('02-应收明细'!N6:N20,">90",'02-应收明细'!J6:J20) -> 3277000 | C9: 逐笔 | D9: 逐笔看客户和证据
A10: 90天以上占比 | B10: =IF(B6=0,0,B9/B6) -> 0.13875598 | C10: 0.08 | D10: 评估信用和ECL
A11: 争议余额 | B11: =SUMIF('02-应收明细'!Q6:Q20,"是",'02-应收明细'!J6:J20) -> 1695000 | C11: 逐笔 | D11: 区分验收、质量、价格
A12: 信用冻结客户数 | B12: =COUNTIF('01-客户信用'!I6:I17,"冻结") -> 2 | C12: 0 | D12: 未经批准不得放货
A13: 未认领回款 | B13: =SUMIF('05-回款认领'!H6:H65,"未认领",'05-回款认领'!D6:D65) -> 226000 | C13: 0 | D13: 当日或次日认领
A14: ECL估计 | B14: =SUM('07-ECL测算'!J6:J20) -> 1655450 | C14: 有依据 | D14: 复核模型和个别评估
A15: Open Issue | B15: =COUNTIF('12-Issue Log'!N6:N65,"Open") -> 2 | C15: 0 | D15: 明确截止和Closure

Sheet 01-客户信用
A1: 客户主数据与信用
A2: 额度、账期、状态和有效期必须经过授权维护。
A5: 客户编码 | B5: 客户名称 | C5: 客户类型 | D5: 信用等级 | E5: 信用额度 | F5: 账期天数 | G5: 责任销售 | H5: 区域 | I5: 信用状态 | J5: 说明
A6: C001 | B6: 华东工业集团 | C6: 国企 | D6: A级 | E6: 5000000 | F6: 60 | G6: 张华 | H6: 华东区 | I6: 正常 | J6: 核心客户，历史回款稳定
A7: C002 | B7: 南方电子科技 | C7: 民营 | D7: B级 | E7: 3000000 | F7: 60 | G7: 李敏 | H7: 华南区 | I7: 关注 | J7: 近期回款放慢
A8: C003 | B8: 北方自动化 | C8: 民营 | D8: C级 | E8: 1500000 | F8: 45 | G8: 王强 | H8: 北方区 | I8: 冻结 | J8: 逾期超过90天且存在验收争议
A9: C004 | B9: 西部设备公司 | C9: 国企 | D9: A级 | E9: 4000000 | F9: 90 | G9: 赵雪 | H9: 西部区 | I9: 正常 | J9: 项目型客户
A10: C005 | B10: 新锐机器人 | C10: 初创 | D10: C级 | E10: 500000 | F10: 30 | G10: 陈晨 | H10: 华东区 | I10: 关注 | J10: 成立时间较短
A11: C006 | B11: 海外贸易代理 | C11: 贸易商 | D11: B级 | E11: 2000000 | F11: 45 | G11: 刘洋 | H11: 海外区 | I11: 正常 | J11: 出口代理结算
A12: C007 | B12: 华中制造 | C12: 民营 | D12: B级 | E12: 1800000 | F12: 60 | G12: 周俊 | H12: 华中区 | I12: 正常
A13: C008 | B13: 东南系统集成 | C13: 民营 | D13: B级 | E13: 1200000 | F13: 45 | G13: 吴迪 | H13: 华南区 | I13: 关注 | J13: 多次延迟验收
A14: C009 | B14: 城市轨道项目部 | C14: 事业单位 | D14: A级 | E14: 6000000 | F14: 120 | G14: 孙磊 | H14: 大客户部 | I14: 正常 | J14: 回款慢但预算来源稳定
A15: C010 | B15: 安达经销商 | C15: 经销商 | D15: C级 | E15: 800000 | F15: 30 | G15: 郑凯 | H15: 渠道部 | I15: 冻结 | J15: 超过额度且逾期
A16: C011 | B16: 长江仪器 | C16: 民营 | D16: B级 | E16: 1500000 | F16: 60 | G16: 李敏 | H16: 华南区 | I16: 正常
A17: C012 | B17: 智联数据中心 | C17: 上市公司 | D17: A级 | E17: 3500000 | F17: 75 | G17: 张华 | H17: 华东区 | I17: 正常

Sheet 02-应收明细
A1: 应收账款明细
A2: 余额、逾期天数和账龄自动计算。账龄基准日：2026-08-31。
A5: 应收ID | B5: 客户编码 | C5: 客户名称 | D5: 开票日 | E5: 到期日 | F5: 订单 | G5: 发票 | H5: 原值 | I5: 已收 | J5: 余额 | K5: 业务状态 | L5: 来源部门 | M5: 信用等级 | N5: 逾期天数 | O5: 账龄段 | P5: 到期状态 | Q5: 争议 | R5: 责任销售
A6: AR001 | B6: C001 | C6: 华东工业集团 | D6: 46230 | E6: 46260 | F6: SO260701 | G6: INV260701 | H6: 1130000 | I6: 0 | J6: 1130000 | K6: 正常 | L6: 销售部 | M6: A级 | N6: =MAX(0,DATE(2026,8,31)-E6) -> 5 | O6: =IF(N6=0,"未到期",IF(N6<=30,"1-30天",IF(N6<=90,"31-90天",IF(N6<=180,"91-180天",IF(N6<=365,"181-365天","365天以上"))))) -> 1-30天 | P6: =IF(DATE(2026,8,31)>E6,"逾期","未到期") -> 逾期 | Q6: 否 | R6: 张华
A7: AR002 | B7: C001 | C7: 华东工业集团 | D7: 46255 | E7: 46315 | F7: SO260812 | G7: INV260812 | H7: 2260000 | I7: 0 | J7: 2260000 | K7: 未到期 | L7: 销售部 | M7: A级 | N7: =MAX(0,DATE(2026,8,31)-E7) -> 0 | O7: =IF(N7=0,"未到期",IF(N7<=30,"1-30天",IF(N7<=90,"31-90天",IF(N7<=180,"91-180天",IF(N7<=365,"181-365天","365天以上"))))) -> 未到期 | P7: =IF(DATE(2026,8,31)>E7,"逾期","未到期") -> 未到期 | Q7: 否 | R7: 张华
A8: AR003 | B8: C002 | C8: 南方电子科技 | D8: 46165 | E8: 46225 | F8: SO260520 | G8: INV260520 | H8: 1695000 | I8: 0 | J8: 1695000 | K8: 催收中 | L8: 销售部 | M8: B级 | N8: =MAX(0,DATE(2026,8,31)-E8) -> 40 | O8: =IF(N8=0,"未到期",IF(N8<=30,"1-30天",IF(N8<=90,"31-90天",IF(N8<=180,"91-180天",IF(N8<=365,"181-365天","365天以上"))))) -> 31-90天 | P8: =IF(DATE(2026,8,31)>E8,"逾期","未到期") -> 逾期 | Q8: 否 | R8: 李敏
A9: AR004 | B9: C003 | C9: 北方自动化 | D9: 46105 | E9: 46150 | F9: SO260320 | G9: INV260320 | H9: 904000 | I9: 0 | J9: 904000 | K9: 验收争议 | L9: 销售部 | M9: C级 | N9: =MAX(0,DATE(2026,8,31)-E9) -> 115 | O9: =IF(N9=0,"未到期",IF(N9<=30,"1-30天",IF(N9<=90,"31-90天",IF(N9<=180,"91-180天",IF(N9<=365,"181-365天","365天以上"))))) -> 91-180天 | P9: =IF(DATE(2026,8,31)>E9,"逾期","未到期") -> 逾期 | Q9: 是 | R9: 王强
A10: AR005 | B10: C004 | C10: 西部设备公司 | D10: 46185 | E10: 46275 | F10: SO260610 | G10: INV260610 | H10: 3390000 | I10: 0 | J10: 3390000 | K10: 未到期 | L10: 销售部 | M10: A级 | N10: =MAX(0,DATE(2026,8,31)-E10) -> 0 | O10: =IF(N10=0,"未到期",IF(N10<=30,"1-30天",IF(N10<=90,"31-90天",IF(N10<=180,"91-180天",IF(N10<=365,"181-365天","365天以上"))))) -> 未到期 | P10: =IF(DATE(2026,8,31)>E10,"逾期","未到期") -> 未到期 | Q10: 否 | R10: 赵雪
A11: AR006 | B11: C005 | C11: 新锐机器人 | D11: 46220 | E11: 46250 | F11: SO260715 | G11: INV260715 | H11: 452000 | I11: 0 | J11: 452000 | K11: 关注 | L11: 销售部 | M11: C级 | N11: =MAX(0,DATE(2026,8,31)-E11) -> 15 | O11: =IF(N11=0,"未到期",IF(N11<=30,"1-30天",IF(N11<=90,"31-90天",IF(N11<=180,"91-180天",IF(N11<=365,"181-365天","365天以上"))))) -> 1-30天 | P11: =IF(DATE(2026,8,31)>E11,"逾期","未到期") -> 逾期 | Q11: 否 | R11: 陈晨
A12: AR007 | B12: C006 | C12: 海外贸易代理 | D12: 46210 | E12: 46255 | F12: SO260705 | G12: INV260705 | H12: 1130000 | I12: 0 | J12: 1130000 | K12: 催收中 | L12: 销售部 | M12: B级 | N12: =MAX(0,DATE(2026,8,31)-E12) -> 10 | O12: =IF(N12=0,"未到期",IF(N12<=30,"1-30天",IF(N12<=90,"31-90天",IF(N12<=180,"91-180天",IF(N12<=365,"181-365天","365天以上"))))) -> 1-30天 | P12: =IF(DATE(2026,8,31)>E12,"逾期","未到期") -> 逾期 | Q12: 否 | R12: 刘洋
A13: AR008 | B13: C007 | C13: 华中制造 | D13: 46235 | E13: 46295 | F13: SO260801 | G13: INV260801 | H13: 2034000 | I13: 0 | J13: 2034000 | K13: 未到期 | L13: 销售部 | M13: B级 | N13: =MAX(0,DATE(2026,8,31)-E13) -> 0 | O13: =IF(N13=0,"未到期",IF(N13<=30,"1-30天",IF(N13<=90,"31-90天",IF(N13<=180,"91-180天",IF(N13<=365,"181-365天","365天以上"))))) -> 未到期 | P13: =IF(DATE(2026,8,31)>E13,"逾期","未到期") -> 未到期 | Q13: 否 | R13: 周俊
A14: AR009 | B14: C008 | C14: 东南系统集成 | D14: 46125 | E14: 46170 | F14: SO260410 | G14: INV260410 | H14: 791000 | I14: 0 | J14: 791000 | K14: 验收争议 | L14: 销售部 | M14: B级 | N14: =MAX(0,DATE(2026,8,31)-E14) -> 95 | O14: =IF(N14=0,"未到期",IF(N14<=30,"1-30天",IF(N14<=90,"31-90天",IF(N14<=180,"91-180天",IF(N14<=365,"181-365天","365天以上"))))) -> 91-180天 | P14: =IF(DATE(2026,8,31)>E14,"逾期","未到期") -> 逾期 | Q14: 是 | R14: 吴迪
A15: AR010 | B15: C009 | C15: 城市轨道项目部 | D15: 46195 | E15: 46315 | F15: SO260620 | G15: INV260620 | H15: 4520000 | I15: 0 | J15: 4520000 | K15: 未到期 | L15: 销售部 | M15: A级 | N15: =MAX(0,DATE(2026,8,31)-E15) -> 0 | O15: =IF(N15=0,"未到期",IF(N15<=30,"1-30天",IF(N15<=90,"31-90天",IF(N15<=180,"91-180天",IF(N15<=365,"181-365天","365天以上"))))) -> 未到期 | P15: =IF(DATE(2026,8,31)>E15,"逾期","未到期") -> 未到期 | Q15: 否 | R15: 孙磊
A16: AR011 | B16: C010 | C16: 安达经销商 | D16: 46135 | E16: 46165 | F16: SO260425 | G16: INV260425 | H16: 1017000 | I16: 0 | J16: 1017000 | K16: 法务评估 | L16: 销售部 | M16: C级 | N16: =MAX(0,DATE(2026,8,31)-E16) -> 100 | O16: =IF(N16=0,"未到期",IF(N16<=30,"1-30天",IF(N16<=90,"31-90天",IF(N16<=180,"91-180天",IF(N16<=365,"181-365天","365天以上"))))) -> 91-180天 | P16: =IF(DATE(2026,8,31)>E16,"逾期","未到期") -> 逾期 | Q16: 否 | R16: 郑凯
A17: AR012 | B17: C011 | C17: 长江仪器 | D17: 46240 | E17: 46300 | F17: SO260806 | G17: INV260806 | H17: 678000 | I17: 0 | J17: 678000 | K17: 未到期 | L17: 销售部 | M17: B级 | N17: =MAX(0,DATE(2026,8,31)-E17) -> 0 | O17: =IF(N17=0,"未到期",IF(N17<=30,"1-30天",IF(N17<=90,"31-90天",IF(N17<=180,"91-180天",IF(N17<=365,"181-365天","365天以上"))))) -> 未到期 | P17: =IF(DATE(2026,8,31)>E17,"逾期","未到期") -> 未到期 | Q17: 否 | R17: 李敏
... A20: AR015 | B20: C002 | C20: 南方电子科技 | D20: 46055 | E20: 46115 | F20: SO260201 | G20: INV260201 | H20: 565000 | I20: 0 | J20: 565000 | K20: 长期逾期 | L20: 销售部 | M20: B级 | N20: =MAX(0,DATE(2026,8,31)-E20) -> 150 | O20: =IF(N20=0,"未到期",IF(N20<=30,"1-30天",IF(N20<=90,"31-90天",IF(N20<=180,"91-180天",IF(N20<=365,"181-365天","365天以上"))))) -> 91-180天 | P20: =IF(DATE(2026,8,31)>E20,"逾期","未到期") -> 逾期 | Q20: 否 | R20: 李敏

Sheet 03-催收计划
A1: 逾期催收计划
A2: 承诺必须具体到金额、日期、联系人和下一步。
A5: 应收ID | B5: 客户编码 | C5: 客户 | D5: 余额 | E5: 逾期天数 | F5: 当前状态 | G5: 逾期原因 | H5: 客户联系人 | I5: 承诺金额 | J5: 责任销售 | K5: 下一步行动 | L5: 下次日期 | M5: 状态
A6: AR001 | B6: C001 | C6: 华东工业集团 | D6: 1130000 | E6: =MAX(0,DATE(2026,8,31)-DATE(2026,8,26)) -> 5 | F6: 正常 | J6: 张华 | M6: 未开始
A7: AR002 | B7: C001 | C7: 华东工业集团 | D7: 2260000 | E7: =MAX(0,DATE(2026,8,31)-DATE(2026,10,20)) -> 0 | F7: 未到期 | J7: 张华 | M7: 未开始
A8: AR003 | B8: C002 | C8: 南方电子科技 | D8: 1695000 | E8: =MAX(0,DATE(2026,8,31)-DATE(2026,7,22)) -> 40 | F8: 催收中 | J8: 李敏 | M8: 未开始
A9: AR004 | B9: C003 | C9: 北方自动化 | D9: 904000 | E9: =MAX(0,DATE(2026,8,31)-DATE(2026,5,8)) -> 115 | F9: 验收争议 | J9: 王强 | M9: 未开始
A10: AR005 | B10: C004 | C10: 西部设备公司 | D10: 3390000 | E10: =MAX(0,DATE(2026,8,31)-DATE(2026,9,10)) -> 0 | F10: 未到期 | J10: 赵雪 | M10: 未开始
A11: AR006 | B11: C005 | C11: 新锐机器人 | D11: 452000 | E11: =MAX(0,DATE(2026,8,31)-DATE(2026,8,16)) -> 15 | F11: 关注 | J11: 陈晨 | M11: 未开始
A12: AR007 | B12: C006 | C12: 海外贸易代理 | D12: 1130000 | E12: =MAX(0,DATE(2026,8,31)-DATE(2026,8,21)) -> 10 | F12: 催收中 | J12: 刘洋 | M12: 未开始
A13: AR008 | B13: C007 | C13: 华中制造 | D13: 2034000 | E13: =MAX(0,DATE(2026,8,31)-DATE(2026,9,30)) -> 0 | F13: 未到期 | J13: 周俊 | M13: 未开始
A14: AR009 | B14: C008 | C14: 东南系统集成 | D14: 791000 | E14: =MAX(0,DATE(2026,8,31)-DATE(2026,5,28)) -> 95 | F14: 验收争议 | J14: 吴迪 | M14: 未开始
A15: AR010 | B15: C009 | C15: 城市轨道项目部 | D15: 4520000 | E15: =MAX(0,DATE(2026,8,31)-DATE(2026,10,20)) -> 0 | F15: 未到期 | J15: 孙磊 | M15: 未开始
A16: AR011 | B16: C010 | C16: 安达经销商 | D16: 1017000 | E16: =MAX(0,DATE(2026,8,31)-DATE(2026,5,23)) -> 100 | F16: 法务评估 | J16: 郑凯 | M16: 未开始
A17: AR012 | B17: C011 | C17: 长江仪器 | D17: 678000 | E17: =MAX(0,DATE(2026,8,31)-DATE(2026,10,5)) -> 0 | F17: 未到期 | J17: 李敏 | M17: 未开始
A18: AR013 | B18: C012 | C18: 智联数据中心 | D18: 2825000 | E18: =MAX(0,DATE(2026,8,31)-DATE(2026,8,16)) -> 15 | F18: 催收中 | J18: 张华 | M18: 未开始
A19: AR014 | B19: C003 | C19: 北方自动化 | D19: 226000 | E19: =MAX(0,DATE(2026,8,31)-DATE(2026,9,25)) -> 0 | F19: 冻结后例外发货 | J19: 王强 | M19: 未开始
A20: AR015 | B20: C002 | C20: 南方电子科技 | D20: 565000 | E20: =MAX(0,DATE(2026,8,31)-DATE(2026,4,3)) -> 150 | F20: 长期逾期 | J20: 李敏 | M20: 未开始

Sheet 04-争议台账
A1: 应收争议台账
A2: 区分验收、质量、价格、发票和信用问题。
A5: 争议ID | B5: 客户 | C5: 应收ID | D5: 类型 | E5: 金额 | F5: 客户主张 | G5: 公司判断 | H5: 责任部门 | I5: 下一步 | J5: 截止日 | K5: 状态 | L5: 会计影响 | M5: 证据路径
A6: DIS-001 | K6: Open
A7: DIS-002 | K7: Open
A8: DIS-003 | K8: Open
A9: DIS-004 | K9: Open
A10: DIS-005 | K10: Open
A11: DIS-006 | K11: Open
A12: DIS-007 | K12: Open
A13: DIS-008 | K13: Open
A14: DIS-009 | K14: Open
A15: DIS-010 | K15: Open
A16: DIS-011 | K16: Open
A17: DIS-012 | K17: Open
... A45: DIS-040 | K45: Open

Sheet 05-回款认领
A1: 银行回款认领
A2: 付款主体、客户和应收项目不确定时转人工确认。
A5: 流水ID | B5: 到账日 | C5: 付款户名 | D5: 金额 | E5: 摘要/订单 | F5: 客户编码 | G5: 应收ID | H5: 认领状态 | I5: 匹配依据 | J5: 责任人
A6: RC001 | B6: 2026-08-31 | C6: 华东商贸 | D6: 1130000 | E6: SO260701 | F6: C001 | G6: AR001 | H6: 已认领 | I6: 金额户名订单一致 | J6: AR会计
A7: RC002 | B7: 2026-08-31 | C7: 未知付款人 | D7: 226000 | H7: 未认领 | I7: 摘要不清，不得按金额随意核销 | J7: 资金
A8: RC003 | H8: 未认领
A9: RC004 | H9: 未认领
A10: RC005 | H10: 未认领
A11: RC006 | H11: 未认领
A12: RC007 | H12: 未认领
A13: RC008 | H13: 未认领
A14: RC009 | H14: 未认领
A15: RC010 | H15: 未认领
A16: RC011 | H16: 未认领
A17: RC012 | H17: 未认领
A18: RC013 | H18: 未认领
A19: RC014 | H19: 未认领
... A65: RC060 | H65: 未认领

Sheet 06-信用审批
A1: 信用额度与例外审批
A2: 记录额度、账期、风险敞口、例外原因和失效日期。
A5: 申请号 | B5: 客户 | C5: 申请类型 | D5: 现有等级 | E5: 现有额度 | F5: 申请额度 | G5: 现有逾期 | H5: 新增订单 | I5: 担保/预付 | J5: 风险分析 | K5: 失效日 | L5: 状态
A6: CR-001 | E6: 0 | F6: 0 | L6: 待审批
A7: CR-002 | E7: 0 | F7: 0 | L7: 待审批
A8: CR-003 | E8: 0 | F8: 0 | L8: 待审批
A9: CR-004 | E9: 0 | F9: 0 | L9: 待审批
A10: CR-005 | E10: 0 | F10: 0 | L10: 待审批
A11: CR-006 | E11: 0 | F11: 0 | L11: 待审批
A12: CR-007 | E12: 0 | F12: 0 | L12: 待审批
A13: CR-008 | E13: 0 | F13: 0 | L13: 待审批
A14: CR-009 | E14: 0 | F14: 0 | L14: 待审批
A15: CR-010 | E15: 0 | F15: 0 | L15: 待审批
A16: CR-011 | E16: 0 | F16: 0 | L16: 待审批
A17: CR-012 | E17: 0 | F17: 0 | L17: 待审批
... A45: CR-040 | E45: 0 | F45: 0 | L45: 待审批

Sheet 07-ECL测算
A1: 预期信用损失测算
A2: 案例比例可修改，不代表统一行业比例。重大客户应个别评估。
A5: 应收ID | B5: 客户 | C5: 余额 | D5: 逾期天数 | E5: 账龄 | F5: 个别评估 | G5: 争议 | H5: 损失率 | I5: 组合ECL | J5: 最终ECL | K5: 判断依据 | L5: 状态
A6: AR001 | B6: 华东工业集团 | C6: 1130000 | D6: ='02-应收明细'!N6 -> 5 | E6: ='02-应收明细'!O6 -> 1-30天 | F6: 否 | G6: 否 | H6: 0.03 | I6: =C6*H6 -> 33900 | J6: =I6 -> 33900 | L6: 待复核
A7: AR002 | B7: 华东工业集团 | C7: 2260000 | D7: ='02-应收明细'!N7 -> 0 | E7: ='02-应收明细'!O7 -> 未到期 | F7: 否 | G7: 否 | H7: 0.03 | I7: =C7*H7 -> 67800 | J7: =I7 -> 67800 | L7: 待复核
A8: AR003 | B8: 南方电子科技 | C8: 1695000 | D8: ='02-应收明细'!N8 -> 40 | E8: ='02-应收明细'!O8 -> 31-90天 | F8: 否 | G8: 否 | H8: 0.03 | I8: =C8*H8 -> 50850 | J8: =I8 -> 50850 | L8: 待复核
A9: AR004 | B9: 北方自动化 | C9: 904000 | D9: ='02-应收明细'!N9 -> 115 | E9: ='02-应收明细'!O9 -> 91-180天 | F9: 否 | G9: 是 | H9: 0.15 | I9: =C9*H9 -> 135600 | J9: =I9 -> 135600 | L9: 待复核
A10: AR005 | B10: 西部设备公司 | C10: 3390000 | D10: ='02-应收明细'!N10 -> 0 | E10: ='02-应收明细'!O10 -> 未到期 | F10: 否 | G10: 否 | H10: 0.03 | I10: =C10*H10 -> 101700 | J10: =I10 -> 101700 | L10: 待复核
A11: AR006 | B11: 新锐机器人 | C11: 452000 | D11: ='02-应收明细'!N11 -> 15 | E11: ='02-应收明细'!O11 -> 1-30天 | F11: 否 | G11: 否 | H11: 0.03 | I11: =C11*H11 -> 13560 | J11: =I11 -> 13560 | L11: 待复核
A12: AR007 | B12: 海外贸易代理 | C12: 1130000 | D12: ='02-应收明细'!N12 -> 10 | E12: ='02-应收明细'!O12 -> 1-30天 | F12: 否 | G12: 否 | H12: 0.03 | I12: =C12*H12 -> 33900 | J12: =I12 -> 33900 | L12: 待复核
A13: AR008 | B13: 华中制造 | C13: 2034000 | D13: ='02-应收明细'!N13 -> 0 | E13: ='02-应收明细'!O13 -> 未到期 | F13: 否 | G13: 否 | H13: 0.03 | I13: =C13*H13 -> 61020 | J13: =I13 -> 61020 | L13: 待复核
A14: AR009 | B14: 东南系统集成 | C14: 791000 | D14: ='02-应收明细'!N14 -> 95 | E14: ='02-应收明细'!O14 -> 91-180天 | F14: 否 | G14: 是 | H14: 0.15 | I14: =C14*H14 -> 118650 | J14: =I14 -> 118650 | L14: 待复核
A15: AR010 | B15: 城市轨道项目部 | C15: 4520000 | D15: ='02-应收明细'!N15 -> 0 | E15: ='02-应收明细'!O15 -> 未到期 | F15: 否 | G15: 否 | H15: 0.03 | I15: =C15*H15 -> 135600 | J15: =I15 -> 135600 | L15: 待复核
A16: AR011 | B16: 安达经销商 | C16: 1017000 | D16: ='02-应收明细'!N16 -> 100 | E16: ='02-应收明细'!O16 -> 91-180天 | F16: 是 | G16: 否 | H16: 0.5 | I16: =C16*H16 -> 508500 | J16: =I16 -> 508500 | L16: 待复核
A17: AR012 | B17: 长江仪器 | C17: 678000 | D17: ='02-应收明细'!N17 -> 0 | E17: ='02-应收明细'!O17 -> 未到期 | F17: 否 | G17: 否 | H17: 0.03 | I17: =C17*H17 -> 20340 | J17: =I17 -> 20340 | L17: 待复核
... A20: AR015 | B20: 南方电子科技 | C20: 565000 | D20: ='02-应收明细'!N20 -> 150 | E20: ='02-应收明细'!O20 -> 91-180天 | F20: 否 | G20: 否 | H20: 0.5 | I20: =C20*H20 -> 282500 | J20: =I20 -> 282500 | L20: 待复核

Sheet 08-核心指标
A1: 应收管理核心指标
A2: 指标恶化后必须向客户、订单、账期、争议和责任销售下钻。
A5: 指标 | B5: 定义 | C5: 管理意义 | D5: 恶化原因 | E5: 下钻方向
A6: 应收账款余额 | B6: 期末应收总额 | C6: 反映资金占用，但必须结合收入规模 | D6: 收入增长、回款变慢、核销延迟或提前确认 | E6: 按客户、账龄、订单和责任销售下钻
A7: 逾期率 | B7: 逾期应收÷应收余额 | C7: 反映账期执行和信用质量 | D7: 客户困难、争议、信用放宽、催收失效 | E7: 区分未到期、技术逾期和实质风险
A8: DSO | B8: 平均应收÷赊销收入×期间天数 | C8: 反映销售转化为现金的速度 | D8: 客户结构、账期、季节、收入截止和回款变化 | E8: 按区域、客户类型和销售人员拆分
A9: 90天以上逾期占比 | B9: 逾期90天以上÷应收余额 | C9: 聚焦高风险和难收款项 | D9: 重大争议、客户恶化、责任不清 | E9: 逐笔指定Owner和法务动作
A10: 信用额度占用率 | B10: 客户未结余额及未开票风险敞口÷额度 | C10: 控制继续接单和发货风险 | D10: 额度过低、订单激增或回款变慢 | E10: 同时查看在途订单、担保和例外审批
A11: 回款预测准确率 | B11: 实际回款÷预测回款或按偏差计算 | C11: 评价现金预测和销售承诺质量 | D11: 销售乐观、客户计划变化、认领延迟 | E11: 分析承诺客户、金额和日期偏差
A12: 争议应收占比 | B12: 争议款÷应收余额 | C12: 区分信用问题和交付质量问题 | D12: 验收、质量、开票、价格或合同问题 | E12: 按争议类型和责任部门分析
A13: 集中度 | B13: 前五大客户应收÷应收余额 | C13: 衡量客户集中和现金风险 | D13: 大客户项目增加或小客户减少 | E13: 评估单一客户违约冲击
A14: 坏账准备覆盖率 | B14: 坏账准备÷应收余额 | C14: 反映减值覆盖但不能脱离风险结构 | D14: 模型参数、组合变化或个别评估 | E14: 与账龄迁徙、核销和回收率联动
A15: 核销及时率 | B15: 已认领收款÷银行收款 | C15: 反映AR数据是否可用于催收和预测 | D15: 摘要不清、主数据差、责任人不反馈 | E15: 查看未认领金额和账龄

Sheet 09-月末Checklist
A1: 应收月末检查清单
A2: 每项必须有执行证据和复核结果。
A5: 明确动作 | B5: 责任人 | C5: 期限 | D5: 证据 | E5: 关闭标准 | F5: 完成状态 | G5: 复核人 | H5: 复核日
A6: 取得AR子模块期末余额并与GL核对 | B6: AR会计 | C6: T+1 | D6: 模块余额、GL、差异明细 | E6: 差异为0或有批准解释 | F6: 未开始
A7: 检查所有逾期90天以上客户并形成逐笔清单 | B7: AR/销售 | C7: T+1 | D7: 账龄、客户状态、催收记录 | E7: 每笔有Owner和下一步 | F7: 未开始
A8: 检查应收贷方余额并追查业务实质 | B8: 总账 | C8: T+2 | D8: 客户明细、收款、发票、退款 | E8: 不得机械重分类 | F8: 未开始
A9: 核对银行回款与AR核销，列示未认领款 | B9: 资金/AR | C9: T+1 | D9: 银行流水、核销日志 | E9: 未认领有责任人 | F9: 未开始
A10: 复核本月新增大额应收及账期例外 | B10: 财务主管 | C10: T+2 | D10: 合同、订单、审批 | E10: 超政策均有审批 | F10: 未开始
A11: 复核收入、开票和应收截止 | B11: 总账 | C11: T+2 | D11: 发货、验收、开票、收入明细 | E11: 跨期差异已处理 | F11: 未开始
A12: 更新争议款清单和预计解决日期 | B12: 销售/项目 | C12: T+2 | D12: 客户异议、质量或验收资料 | E12: 责任部门和截止明确 | F12: 未开始
A13: 复核ECL模型、账龄迁徙和个别评估 | B13: 财务主管 | C13: T+3 | D13: ECL底稿、法务和销售信息 | E13: 假设有证据并经审批 | F13: 未开始
A14: 核对客户对账覆盖率和重大未回函 | B14: AR | C14: T+3 | D14: 对账函、替代证据 | E14: 重大余额有证据 | F14: 未开始
A15: 更新信用额度占用和冻结客户 | B15: 信用管理 | C15: 月末 | D15: 额度、应收、在途订单 | E15: 系统状态一致 | F15: 未开始
A16: 形成应收管理一页报告 | B16: 财务主管 | C16: T+4 | D16: 余额、逾期、回款和风险 | E16: 结论、行动、Owner和期限齐全 | F16: 未开始
A17: 归档月结底稿和复核证据 | B17: 总账 | C17: T+4 | D17: 底稿目录 | E17: 文件可追溯 | F17: 未开始

Sheet 10-接手检查
A1: 新财务主管接手检查
A2: 记录已取得资料、发现和责任边界。
A5: 阶段 | B5: 事项 | C5: 检查动作 | D5: 发现/证据 | E5: 状态
A6: 第一周 | B6: 客户主数据和信用权限 | C6: 确认谁能创建、修改和审批 | E6: 未开始
A7: 第一周 | B7: AR明细与GL | C7: 重做模块总账对账 | E7: 未开始
A8: 第一周 | B8: 账龄和逾期 | C8: 重算到期日与逾期天数 | E8: 未开始
A9: 第一周 | B9: 重大客户对账 | C9: 抽查前十大客户 | E9: 未开始
A10: 第一月 | B10: 信用冻结和例外 | C10: 检查冻结客户是否仍发货 | E10: 未开始
A11: 第一月 | B11: ECL和核销 | C11: 复核模型、个别评估和审批 | E11: 未开始
A12: 第一月 | B12: 争议和诉讼 | C12: 与法务核对完整性 | E12: 未开始
A13: 第一月 | B13: 历史问题边界 | C13: 形成基准日问题清单并汇报 | E13: 未开始

Sheet 11-风险红旗
A1: 应收风险红旗
A2: 发现后先控制风险，再核实和升级。
A5: 控制 | B5: 风险 | C5: 控制动作 | D5: 证据
A6: 客户主数据创建与销售审批分离 | B6: 虚构客户或绕过信用 | C6: 客户创建人不能审批信用和发货例外 | D6: IT权限清单、审批记录
A7: 信用评估与合同审批分离 | B7: 销售为冲业绩放宽账期 | C7: 额度和账期超政策需独立审批 | D7: 信用审批单
A8: 发货受信用额度控制 | B8: 超额、逾期继续发货 | C8: ERP自动冻结，例外有金额和期限 | D8: 放货日志
A9: 开票依据完整 | B9: 提前或虚假开票 | C9: 按发货、验收和合同条件开票 | D9: 发票、出库、验收
A10: 收款与核销分离 | B10: 挪用或错配回款 | C10: 资金确认到账，AR核销，主管复核 | D10: 流水和核销日志
A11: 客户对账定期执行 | B11: 长期差异被掩盖 | C11: 按风险分层对账并跟踪未回函 | D11: 对账函及替代证据
A12: 坏账计提与审批分离 | B12: 利润操纵 | C12: 模型参数、个别评估和审批留痕 | D12: ECL底稿
A13: 坏账核销账销案存 | B13: 核销后私收形成账外资金 | C13: 核销台账继续追踪，收回应入账 | D13: 核销备查簿

Sheet 12-Issue Log
A1: 应收Issue与Closure
A2: Resolved后仍要验证账务、信用状态和业务限制。
A5: Issue | B5: 客户 | C5: 问题 | D5: 来源 | E5: 金额 | F5: 影响 | G5: Owner | H5: 下一步 | I5: 截止日 | J5: 临时控制 | K5: 会计处理 | L5: 管理整改 | M5: 复核人 | N5: 状态 | O5: Closure证据
A6: ISS-001 | B6: 北方自动化 | C6: 逾期115天且存在验收争议 | D6: 月结 | E6: 904000 | F6: 现金、减值和收入 | G6: 销售总监 | H6: 完成客户验收争议方案 | I6: 46280 | J6: 冻结新增发货 | K6: 个别评估ECL | L6: 销售与项目联合关闭 | M6: 财务主管 | N6: Open
A7: ISS-002 | B7: 安达经销商 | C7: 超额度且逾期100天 | D7: 信用检查 | E7: 1017000 | F7: 现金和信用 | G7: 渠道总监 | H7: 取得回款并重评额度 | I7: 46275 | J7: 冻结发货 | K7: 评估ECL | L7: 按回款恢复额度 | M7: 财务经理 | N7: Open
A8: ISS-003 | B8: 未知付款人 | C8: 22.6万元回款未认领 | D8: 银行对账 | E8: 226000 | F8: 客户账龄和现金预测 | G8: 资金主管 | H8: 确认付款主体和用途 | I8: 46267 | J8: 暂挂未认领款 | K8: 确认后核销 | L8: 完善付款附言规则 | M8: 财务主管 | N8: In Progress
A9: ISS-004 | E9: 0
A10: ISS-005 | E10: 0
A11: ISS-006 | E11: 0
A12: ISS-007 | E12: 0
A13: ISS-008 | E13: 0
A14: ISS-009 | E14: 0
A15: ISS-010 | E15: 0
A16: ISS-011 | E16: 0
A17: ISS-012 | E17: 0
A18: ISS-013 | E18: 0
A19: ISS-014 | E19: 0
A20: ISS-015 | E20: 0
... A65: ISS-060 | E65: 0

Sheet 13-RACI
A1: 岗位责任矩阵
A2: 业务对真实性和催收行动负责，财务对数据、监督和专业判断负责。
A5: 事项 | B5: 执行 | C5: 财务主管 | D5: 协同 | E5: 批准
A6: 客户准入 | B6: 销售 | C6: 信用管理/财务 | D6: 法务、税务 | E6: 财务经理
A7: 信用额度 | B7: 销售提供资料 | C7: 财务分析 | D7: 销售总监 | E7: 按权限审批
A8: 合同和账期 | B8: 销售/法务 | C8: 财务审核财务条款 | D8: 税务、交付部门 | E8: 授权人
A9: 发货放行 | B9: 仓库/销售 | C9: 系统按额度校验 | D9: AR/信用管理 | E9: 例外审批人
A10: 收入和应收 | B10: 总账/AR | C10: 财务主管复核 | D10: 销售、项目 | E10: 财务经理重大判断
A11: 催收 | B11: 销售Owner | C11: AR提供清单并跟踪 | D11: 法务 | E11: 销售负责人
A12: 回款认领 | B12: 资金/AR | C12: 财务主管复核未认领 | D12: 销售 | E12: 财务经理重大异常
A13: 坏账准备 | B13: 总账编制 | C13: 财务主管复核模型 | D13: 销售、法务 | E13: 财务经理审批
A14: 坏账核销 | B14: AR/总账发起 | C14: 财务主管核查证据 | D14: 法务、销售 | E14: 按权限审批
A15: 客户对账 | B15: 销售/AR | C15: 财务主管监督覆盖率 | D15: 客户 | E15: 重大差异升级

Sheet 14-案例库
A1: 应收管理典型案例
A2: 逐项填写自己的判断和行动方案。
A5: 编号 | B5: 场景 | C5: 第一步 | D5: 沟通对象 | E5: 处理方案 | F5: 升级条件 | G5: 我的回答
A6: AR-C01 | B6: 客户逾期90天，销售要求继续发货 | C6: 先冻结自动放货，核对额度、逾期原因、客户偿付能力和新增订单毛利 | D6: 销售总监、法务、财务经理 | E6: 信用例外审批、明确回款前置条件和失效日期 | F6: 重大逾期继续扩大且无审批时升级总经理
A7: AR-C02 | B7: 客户称未验收所以拒付，但销售已确认收入 | C7: 取得合同、验收条款、签收、现场记录和客户书面异议 | D7: 销售、项目、法务、总账 | E7: 区分真实履约争议、收入确认错误和单纯付款拖延 | F7: 可能影响收入和报表时立即升级
A8: AR-C03 | B8: 银行收到113万元但摘要不清 | C8: 不得凭金额随意核销，先查付款户名、历史回款和客户确认 | D8: 资金、AR、销售 | E8: 生成高置信度候选，客户或销售书面确认后核销 | F8: 长期无法认领列入月结Issue
A9: AR-C04 | B9: 销售要求把逾期原因写成客户走流程 | C9: 要求提供客户付款计划、联系人、审批节点和证据 | D9: 销售负责人 | E9: 原因必须具体、可验证并设下次行动日 | F9: 连续两期空泛说明升级
A10: AR-C05 | B10: 同一客户在应收和合同负债同时有余额 | C10: 按合同、项目、客户法人和抵销条件逐笔核对 | D10: 总账、销售、法务 | E10: 不能因同一客户就自动净额列示 | F10: 重大列报影响升级财务经理
A11: AR-C06 | B11: 客户要求把发票改开给关联公司 | C11: 核实合同、实际交易、付款义务及三方安排 | D11: 销售、税务、法务 | E11: 主体不一致需合法业务安排和完整证据 | F11: 拒绝无真实安排的换票要求
A12: AR-C07 | B12: 对账函客户不回 | C12: 通过邮件、门户、签收、后续回款和业务确认取得替代证据 | D12: 销售、AR | E12: 列明未回函原因和替代证据 | F12: 重大长期余额转法务评估
A13: AR-C08 | B13: 销售把回款奖金作为唯一目标 | C13: 分析是否诱导提前压货、异常退款或短期行为 | D13: 销售管理层、HR | E13: 收入、毛利、回款、逾期和退货联合考核 | F13: 政策调整由财务经理推动
A14: AR-C09 | B14: 客户破产但账龄只有60天 | C14: 启动个别评估，不机械套用账龄比例 | D14: 法务、销售、财务经理 | E14: 结合破产信息、担保、受偿顺序和预计现金流计提 | F14: 重大减值及时报告管理层
A15: AR-C10 | B15: 以前年度坏账已核销，本期又收回 | C15: 核对原核销审批、到账和客户 | D15: AR、总账 | E15: 账销案存并按准则进行收回处理 | F15: 防止形成账外资金
A16: AR-C11 | B16: 客户以质量问题抵扣货款 | C16: 取得质量报告、索赔条款、退换货和双方确认 | D16: 质量、销售、法务 | E16: 区分折让、退款、赔偿和无依据扣款 | F16: 影响收入、税务或产品质量时升级
A17: AR-C12 | B17: 销售人员私下承诺延长账期 | C17: 核对权限、邮件、合同变更和客户证据 | D17: 销售总监、法务 | E17: 未经授权承诺不得自动改变系统信用条件 | F17: 评估表见代理及法律风险
... A20: AR-C15 | B20: 老板要求不给长期客户计提坏账 | C20: 以预期信用损失证据和敏感性测算说明影响 | D20: 财务经理、总经理 | E20: 不能因关系好或关联方身份免于评估 | F20: 涉及报表失真时书面升级

Sheet 15-资料来源
A1: 准则 法律与内控依据
A2: 区分会计准则、法律、内控指引和企业内部政策。
A5: 名称 | B5: 文件号 | C5: 关系 | D5: 官方网址
A6: 企业会计准则第14号 收入 | B6: 财会〔2017〕22号 | C6: 收入确认、合同资产与应收款边界 | D6: https://kjs.mof.gov.cn/zt/kjzzss/kuaijizhunzeshishi/201709/t20170907_2694006.htm
A7: 企业会计准则第22号 金融工具确认和计量 | B7: 财会〔2017〕7号 | C7: 预期信用损失、减值计量 | D7: https://www.mof.gov.cn/zcsjtsgb/gfxwj/201703/t20170331_3583504.htm
A8: 关于严格执行企业会计准则切实做好企业2025年年报工作的通知 | B8: 财政部会计司 2025年通知 | C8: 不得无依据少提应收款项预期信用损失 | D8: https://kjs.mof.gov.cn/gongzuotongzhi/202512/t20251224_3980024.htm
A9: 企业内部控制应用指引第9号 销售业务 | B9: 财会〔2010〕11号配套指引 | C9: 信用、发货、收款、对账、坏账和职责分离 | D9: https://www.mof.gov.cn/gp/xxgkml/hjs/201005/P020100518351827137241.pdf
A10: 中华人民共和国民法典 | B10: 主席令第四十五号 | C10: 一般诉讼时效、时效中断等 | D10: https://www.cac.gov.cn/2020-06/01/c_1592561777268319.htm
