Workbook

Sheet 00-管理看板
A1: 应付账款及供应商管理工具包
A2: 案例企业：华辰智造科技有限公司。账龄基准日2026-08-31，黄色区域为人工维护。
A5: 指标 | B5: 本期结果 | C5: 管理阈值 | D5: 主管动作
A6: 应付净余额 | B6: =SUM('02-应付明细'!K6:K23) -> 12707500 | C6: 结合采购额 | D6: 解释采购与付款变化
A7: 逾期正余额 | B7: =SUMIF('02-应付明细'!R6:R23,"逾期",'02-应付明细'!K6:K23) -> 4915000 | C7: 逐笔 | D7: 区分无争议与争议
A8: 逾期率 | B8: =IF(B6=0,0,B7/B6) -> 0.38677946 | C8: 0.1 | D8: 超过阈值专项分析
A9: 未来30天到期 | B9: =SUMIFS('02-应付明细'!K6:K23,'02-应付明细'!E6:E23,">="&DATE(2026,9,1),'02-应付明细'!E6:E23,"<="&DATE(2026,9,30),'02-应付明细'!K6:K23,">0") -> 5480500 | C9: 现金计划 | D9: 纳入13周预测
A10: 暂估未到票 | B10: =SUMIF('02-应付明细'!L6:L23,"暂估未到票",'02-应付明细'!K6:K23) -> 3390000 | C10: >60天逐笔 | D10: 追发票并查真实义务
A11: 争议余额 | B11: =SUMIF('02-应付明细'!M6:M23,"是",'02-应付明细'!K6:K23) -> 1634000 | C11: 逐笔 | D11: 付款与索赔分开
A12: 应付负余额 | B12: =-SUMIF('02-应付明细'!K6:K23,"<0",'02-应付明细'!K6:K23) -> 61000 | C12: 0 | D12: 查预付/超付/串户
A13: 冻结供应商数 | B13: =COUNTIF('01-供应商主数据'!H6:H17,"冻结") -> 1 | C13: 0 | D13: 冻结交易与付款
A14: 账户变更待核验 | B14: =COUNTIF('07-账户变更'!J6:J45,"待核验") -> 1 | C14: 0 | D14: 独立回拨验证
A15: 逾期预付 | B15: =SUMIF('10-预付跟踪'!J6:J45,"逾期",'10-预付跟踪'!E6:E45) -> 300000 | C15: 0 | D15: 追履约或退款
A16: Open Issue | B16: =COUNTIF('15-Issue Log'!N6:N65,"Open") -> 2 | C16: 0 | D16: Owner、日期、临时控制和Closure

Sheet 01-供应商主数据
A1: 供应商主数据与准入
A2: 供应商创建、银行账户维护、发票处理和付款职责应分离。
A5: 编码 | B5: 供应商名称 | C5: 类别 | D5: 等级 | E5: 纳税人类型 | F5: 账期 | G5: 额度 | H5: 状态 | I5: 责任部门 | J5: 银行账户 | K5: 复评到期日 | L5: 说明
A6: S001 | B6: 芯联电子科技有限公司 | C6: 芯片/核心料 | D6: A | E6: 一般纳税人 | F6: 60天 | G6: 8000000 | H6: 正常 | I6: 采购一部 | J6: 6222****1010 | K6: 2026-12-31 | L6: 核心供应商，双来源计划
A7: S002 | B7: 东莞精工金属有限公司 | C7: 结构件 | D7: A | E7: 一般纳税人 | F7: 45天 | G7: 4500000 | H7: 正常 | I7: 采购一部 | J7: 6214****2088 | K7: 2026-10-31 | L7: 月度对账
A8: S003 | B8: 华南塑胶科技有限公司 | C8: 塑胶件 | D8: B | E8: 一般纳税人 | F8: 30天 | G8: 2800000 | H8: 关注 | I8: 采购二部 | J8: 6228****6609 | K8: 2026-09-30 | L8: 质量扣款争议
A9: S004 | B9: 云启软件服务有限公司 | C9: 软件/SaaS | D9: B | E9: 一般纳税人 | F9: 预付 | G9: 1200000 | H9: 正常 | I9: IT | J9: 6217****3301 | K9: 2027-03-31 | L9: 需按服务期摊销
A10: S005 | B10: 迅捷物流有限公司 | C10: 物流服务 | D10: B | E10: 一般纳税人 | F10: 月结30天 | G10: 1000000 | H10: 正常 | I10: 物流部 | J10: 6214****7788 | K10: 2026-11-30 | L10: 运费需匹配发运单
A11: S006 | B11: 德信咨询有限公司 | C11: 咨询服务 | D11: C | E11: 一般纳税人 | F11: 验收后30天 | G11: 600000 | H11: 关注 | I11: 总经办 | J11: 6222****4502 | K11: 2026-09-15 | L11: 成果验收后付款
A12: S007 | B12: 力源设备股份有限公司 | C12: 生产设备 | D12: A | E12: 一般纳税人 | F12: 30/60/10 | G12: 6000000 | H12: 正常 | I12: 设备部 | J12: 6214****8921 | K12: 2027-02-28 | L12: 预付及验收尾款
A13: S008 | B13: 华南包装有限公司 | C13: 包装物 | D13: B | E13: 一般纳税人 | F13: 45天 | G13: 1500000 | H13: 正常 | I13: 采购二部 | J13: 6217****5551 | K13: 2026-12-31 | L13: 价格波动较大
A14: S009 | B14: 绿能电力服务有限公司 | C14: 能源 | D14: A | E14: 一般纳税人 | F14: 月结15天 | G14: 2500000 | H14: 正常 | I14: 行政部 | J14: 6228****9900 | K14: 2026-12-31 | L14: 抄表数据匹配
A15: S010 | B15: 瑞诚劳务服务有限公司 | C15: 劳务外包 | D15: B | E15: 一般纳税人 | F15: 验收后30天 | G15: 1800000 | H15: 正常 | I15: HR | J15: 6214****3112 | K15: 2026-10-31 | L15: 人员名单和工时验收
A16: S011 | B16: 宏达贸易有限公司 | C16: 辅料 | D16: D | E16: 一般纳税人 | F16: 30天 | G16: 500000 | H16: 冻结 | I16: 采购二部 | J16: 6222****7180 | K16: 2026-08-31 | L16: 银行账户变更异常
A17: S012 | B17: 华辰供应链有限公司 | C17: 关联方采购 | D17: B | E17: 一般纳税人 | F17: 60天 | G17: 3000000 | H17: 关注 | I17: 供应链 | J17: 6217****8116 | K17: 2026-12-31 | L17: 需关联交易定价证据

Sheet 02-应付明细
A1: 应付账款未清项
A2: 到期、账龄和状态自动计算。先查实质，再处理负余额。
A5: 应付ID | B5: 供应商编码 | C5: 供应商 | D5: 业务日 | E5: 到期日 | F5: PO | G5: 收货/验收 | H5: 发票 | I5: 原值 | J5: 已付 | K5: 余额 | L5: 业务状态 | M5: 争议 | N5: 责任部门 | O5: 备注 | P5: 逾期天数 | Q5: 账龄 | R5: 到期状态
A6: AP001 | B6: S001 | C6: 芯联电子科技有限公司 | D6: 46205 | E6: 46266 | F6: PO260701 | G6: GR260701 | H6: INV260710 | I6: 2260000 | J6: 0 | K6: 2260000 | L6: 待付款 | M6: 否 | N6: 采购一部 | O6: 核心料正常到期 | P6: =MAX(0,DATE(2026,8,31)-E6) -> 0 | Q6: =IF(P6=0,"未到期",IF(P6<=30,"1-30天",IF(P6<=90,"31-90天",IF(P6<=180,"91-180天",IF(P6<=365,"181-365天","365天以上"))))) -> 未到期 | R6: =IF(AND(K6>0,DATE(2026,8,31)>E6),"逾期",IF(K6<0,"负余额","未到期")) -> 未到期
A7: AP002 | B7: S001 | C7: 芯联电子科技有限公司 | D7: 46252 | E7: 46312 | F7: PO260818 | G7: GR260818 | I7: 1695000 | J7: 0 | K7: 1695000 | L7: 暂估未到票 | M7: 否 | N7: 采购一部 | O7: 已入库未收票 | P7: =MAX(0,DATE(2026,8,31)-E7) -> 0 | Q7: =IF(P7=0,"未到期",IF(P7<=30,"1-30天",IF(P7<=90,"31-90天",IF(P7<=180,"91-180天",IF(P7<=365,"181-365天","365天以上"))))) -> 未到期 | R7: =IF(AND(K7>0,DATE(2026,8,31)>E7),"逾期",IF(K7<0,"负余额","未到期")) -> 未到期
A8: AP003 | B8: S002 | C8: 东莞精工金属有限公司 | D8: 46193 | E8: 46238 | F8: PO260620 | G8: GR260620 | H8: INV260625 | I8: 1356000 | J8: 500000 | K8: 856000 | L8: 逾期 | M8: 否 | N8: 采购一部 | O8: 部分付款 | P8: =MAX(0,DATE(2026,8,31)-E8) -> 27 | Q8: =IF(P8=0,"未到期",IF(P8<=30,"1-30天",IF(P8<=90,"31-90天",IF(P8<=180,"91-180天",IF(P8<=365,"181-365天","365天以上"))))) -> 1-30天 | R8: =IF(AND(K8>0,DATE(2026,8,31)>E8),"逾期",IF(K8<0,"负余额","未到期")) -> 逾期
A9: AP004 | B9: S003 | C9: 华南塑胶科技有限公司 | D9: 46152 | E9: 46182 | F9: PO260510 | G9: GR260510 | H9: INV260515 | I9: 904000 | J9: 0 | K9: 904000 | L9: 冻结争议 | M9: 是 | N9: 采购二部 | O9: 质量扣款90,400待确认 | P9: =MAX(0,DATE(2026,8,31)-E9) -> 83 | Q9: =IF(P9=0,"未到期",IF(P9<=30,"1-30天",IF(P9<=90,"31-90天",IF(P9<=180,"91-180天",IF(P9<=365,"181-365天","365天以上"))))) -> 31-90天 | R9: =IF(AND(K9>0,DATE(2026,8,31)>E9),"逾期",IF(K9<0,"负余额","未到期")) -> 逾期
A10: AP005 | B10: S004 | C10: 云启软件服务有限公司 | D10: 46235 | E10: 46235 | F10: PO260801 | G10: SR260801 | H10: INV260801 | I10: 678000 | J10: 678000 | K10: 0 | L10: 预付待摊 | M10: 否 | N10: IT | O10: 一年期SaaS，非应付余额 | P10: =MAX(0,DATE(2026,8,31)-E10) -> 30 | Q10: =IF(P10=0,"未到期",IF(P10<=30,"1-30天",IF(P10<=90,"31-90天",IF(P10<=180,"91-180天",IF(P10<=365,"181-365天","365天以上"))))) -> 1-30天 | R10: =IF(AND(K10>0,DATE(2026,8,31)>E10),"逾期",IF(K10<0,"负余额","未到期")) -> 未到期
A11: AP006 | B11: S005 | C11: 迅捷物流有限公司 | D11: 46234 | E11: 46264 | F11: PO260731 | G11: SR260731 | H11: INV260805 | I11: 339000 | J11: 0 | K11: 339000 | L11: 逾期 | M11: 否 | N11: 物流部 | O11: 部分运单缺失 | P11: =MAX(0,DATE(2026,8,31)-E11) -> 1 | Q11: =IF(P11=0,"未到期",IF(P11<=30,"1-30天",IF(P11<=90,"31-90天",IF(P11<=180,"91-180天",IF(P11<=365,"181-365天","365天以上"))))) -> 1-30天 | R11: =IF(AND(K11>0,DATE(2026,8,31)>E11),"逾期",IF(K11<0,"负余额","未到期")) -> 逾期
A12: AP007 | B12: S006 | C12: 德信咨询有限公司 | D12: 46218 | E12: 46248 | F12: PO260715 | H12: INV260720 | I12: 565000 | J12: 0 | K12: 565000 | L12: 发票先到未验收 | M12: 是 | N12: 总经办 | O12: 成果报告未验收 | P12: =MAX(0,DATE(2026,8,31)-E12) -> 17 | Q12: =IF(P12=0,"未到期",IF(P12<=30,"1-30天",IF(P12<=90,"31-90天",IF(P12<=180,"91-180天",IF(P12<=365,"181-365天","365天以上"))))) -> 1-30天 | R12: =IF(AND(K12>0,DATE(2026,8,31)>E12),"逾期",IF(K12<0,"负余额","未到期")) -> 逾期
A13: AP008 | B13: S007 | C13: 力源设备股份有限公司 | D13: 46246 | E13: 46276 | F13: PO260501 | G13: FA260812 | H13: INV260812 | I13: 2260000 | J13: 1130000 | K13: 1130000 | L13: 设备尾款 | M13: 否 | N13: 设备部 | O13: 验收后付50% | P13: =MAX(0,DATE(2026,8,31)-E13) -> 0 | Q13: =IF(P13=0,"未到期",IF(P13<=30,"1-30天",IF(P13<=90,"31-90天",IF(P13<=180,"91-180天",IF(P13<=365,"181-365天","365天以上"))))) -> 未到期 | R13: =IF(AND(K13>0,DATE(2026,8,31)>E13),"逾期",IF(K13<0,"负余额","未到期")) -> 未到期
A14: AP009 | B14: S008 | C14: 华南包装有限公司 | D14: 46259 | E14: 46304 | F14: PO260825 | G14: GR260825 | H14: INV260827 | I14: 452000 | J14: 0 | K14: 452000 | L14: 待付款 | M14: 否 | N14: 采购二部 | O14: 正常 | P14: =MAX(0,DATE(2026,8,31)-E14) -> 0 | Q14: =IF(P14=0,"未到期",IF(P14<=30,"1-30天",IF(P14<=90,"31-90天",IF(P14<=180,"91-180天",IF(P14<=365,"181-365天","365天以上"))))) -> 未到期 | R14: =IF(AND(K14>0,DATE(2026,8,31)>E14),"逾期",IF(K14<0,"负余额","未到期")) -> 未到期
A15: AP010 | B15: S009 | C15: 绿能电力服务有限公司 | D15: 46265 | E15: 46280 | F15: PO260831 | G15: SR260831 | I15: 791000 | J15: 0 | K15: 791000 | L15: 暂估未到票 | M15: 否 | N15: 行政部 | O15: 按抄表暂估 | P15: =MAX(0,DATE(2026,8,31)-E15) -> 0 | Q15: =IF(P15=0,"未到期",IF(P15<=30,"1-30天",IF(P15<=90,"31-90天",IF(P15<=180,"91-180天",IF(P15<=365,"181-365天","365天以上"))))) -> 未到期 | R15: =IF(AND(K15>0,DATE(2026,8,31)>E15),"逾期",IF(K15<0,"负余额","未到期")) -> 未到期
A16: AP011 | B16: S010 | C16: 瑞诚劳务服务有限公司 | D16: 46234 | E16: 46264 | F16: PO260731L | G16: SR260731L | H16: INV260805L | I16: 1130000 | J16: 0 | K16: 1130000 | L16: 逾期 | M16: 否 | N16: HR | O16: 考勤与名单已验收 | P16: =MAX(0,DATE(2026,8,31)-E16) -> 1 | Q16: =IF(P16=0,"未到期",IF(P16<=30,"1-30天",IF(P16<=90,"31-90天",IF(P16<=180,"91-180天",IF(P16<=365,"181-365天","365天以上"))))) -> 1-30天 | R16: =IF(AND(K16>0,DATE(2026,8,31)>E16),"逾期",IF(K16<0,"负余额","未到期")) -> 逾期
A17: AP012 | B17: S011 | C17: 宏达贸易有限公司 | D17: 46244 | E17: 46274 | F17: PO260810 | G17: GR260810 | H17: INV260812M | I17: 226000 | J17: 0 | K17: 226000 | L17: 付款冻结 | M17: 是 | N17: 采购二部 | O17: 邮件要求改付个人账户 | P17: =MAX(0,DATE(2026,8,31)-E17) -> 0 | Q17: =IF(P17=0,"未到期",IF(P17<=30,"1-30天",IF(P17<=90,"31-90天",IF(P17<=180,"91-180天",IF(P17<=365,"181-365天","365天以上"))))) -> 未到期 | R17: =IF(AND(K17>0,DATE(2026,8,31)>E17),"逾期",IF(K17<0,"负余额","未到期")) -> 未到期
A18: AP013 | B18: S012 | C18: 华辰供应链有限公司 | D18: 46203 | E18: 46263 | F18: PO260630 | G18: GR260630 | H18: INV260705 | I18: 1808000 | J18: 800000 | K18: 1008000 | L18: 逾期关联方 | M18: 否 | N18: 供应链 | O18: 需核对定价与抵销 | P18: =MAX(0,DATE(2026,8,31)-E18) -> 2 | Q18: =IF(P18=0,"未到期",IF(P18<=30,"1-30天",IF(P18<=90,"31-90天",IF(P18<=180,"91-180天",IF(P18<=365,"181-365天","365天以上"))))) -> 1-30天 | R18: =IF(AND(K18>0,DATE(2026,8,31)>E18),"逾期",IF(K18<0,"负余额","未到期")) -> 逾期
A19: AP014 | B19: S002 | C19: 东莞精工金属有限公司 | D19: 45703 | E19: 45748 | F19: PO250215 | G19: GR250215 | H19: INV250220 | I19: 113000 | J19: 0 | K19: 113000 | L19: 长期挂账 | M19: 否 | N19: 采购一部 | O19: 供应商称已收款，可能错付/错核销 | P19: =MAX(0,DATE(2026,8,31)-E19) -> 517 | Q19: =IF(P19=0,"未到期",IF(P19<=30,"1-30天",IF(P19<=90,"31-90天",IF(P19<=180,"91-180天",IF(P19<=365,"181-365天","365天以上"))))) -> 365天以上 | R19: =IF(AND(K19>0,DATE(2026,8,31)>E19),"逾期",IF(K19<0,"负余额","未到期")) -> 逾期
A20: AP015 | B20: S003 | C20: 华南塑胶科技有限公司 | D20: 46263 | E20: 46293 | F20: PO260829 | G20: GR260829 | H20: INV260830 | I20: 339000 | J20: 400000 | K20: -61000 | L20: 负余额 | M20: 是 | N20: 采购二部 | O20: 付款超过本发票，需查预付或串户 | P20: =MAX(0,DATE(2026,8,31)-E20) -> 0 | Q20: =IF(P20=0,"未到期",IF(P20<=30,"1-30天",IF(P20<=90,"31-90天",IF(P20<=180,"91-180天",IF(P20<=365,"181-365天","365天以上"))))) -> 未到期 | R20: =IF(AND(K20>0,DATE(2026,8,31)>E20),"逾期",IF(K20<0,"负余额","未到期")) -> 负余额
A21: AP016 | B21: S008 | C21: 华南包装有限公司 | D21: 46264 | E21: 46309 | F21: PO260830 | G21: GR260830 | H21: INV260831 | I21: 226000 | J21: 0 | K21: 226000 | L21: 待付款 | M21: 否 | N21: 采购二部 | O21: 数量价差在容差内 | P21: =MAX(0,DATE(2026,8,31)-E21) -> 0 | Q21: =IF(P21=0,"未到期",IF(P21<=30,"1-30天",IF(P21<=90,"31-90天",IF(P21<=180,"91-180天",IF(P21<=365,"181-365天","365天以上"))))) -> 未到期 | R21: =IF(AND(K21>0,DATE(2026,8,31)>E21),"逾期",IF(K21<0,"负余额","未到期")) -> 未到期
A22: AP017 | B22: S005 | C22: 迅捷物流有限公司 | D22: 46254 | E22: 46284 | F22: PO260820 | G22: SR260820 | H22: INV260825 | I22: 169500 | J22: 0 | K22: 169500 | L22: 待付款 | M22: 否 | N22: 物流部 | O22: 正常 | P22: =MAX(0,DATE(2026,8,31)-E22) -> 0 | Q22: =IF(P22=0,"未到期",IF(P22<=30,"1-30天",IF(P22<=90,"31-90天",IF(P22<=180,"91-180天",IF(P22<=365,"181-365天","365天以上"))))) -> 未到期 | R22: =IF(AND(K22>0,DATE(2026,8,31)>E22),"逾期",IF(K22<0,"负余额","未到期")) -> 未到期
A23: AP018 | B23: S010 | C23: 瑞诚劳务服务有限公司 | D23: 46265 | E23: 46295 | F23: PO260831L | G23: SR260831L | I23: 904000 | J23: 0 | K23: 904000 | L23: 暂估未到票 | M23: 否 | N23: HR | O23: 8月劳务暂估 | P23: =MAX(0,DATE(2026,8,31)-E23) -> 0 | Q23: =IF(P23=0,"未到期",IF(P23<=30,"1-30天",IF(P23<=90,"31-90天",IF(P23<=180,"91-180天",IF(P23<=365,"181-365天","365天以上"))))) -> 未到期 | R23: =IF(AND(K23>0,DATE(2026,8,31)>E23),"逾期",IF(K23<0,"负余额","未到期")) -> 未到期

Sheet 03-GRNI暂估
A1: 已收货未到票与暂估
A2: 超过60天项目必须查明真实义务、发票计划和清理方案。
A5: GRNI ID | B5: 供应商编码 | C5: 供应商 | D5: PO | E5: 收货/验收 | F5: 收货日 | G5: 暂估金额 | H5: 账龄天数 | I5: 预计到票日 | J5: 责任部门 | K5: 状态 | L5: 差异/处理
A6: GRNI-001 | B6: S001 | C6: 芯联电子科技有限公司 | D6: PO260818 | E6: GR260818 | F6: 46252 | G6: 1695000 | H6: =MAX(0,DATE(2026,8,31)-F6) -> 13 | J6: 采购一部 | K6: 未开始
A7: GRNI-002 | B7: S009 | C7: 绿能电力服务有限公司 | D7: PO260831 | E7: SR260831 | F7: 46265 | G7: 791000 | H7: =MAX(0,DATE(2026,8,31)-F7) -> 0 | J7: 行政部 | K7: 未开始
A8: GRNI-003 | B8: S010 | C8: 瑞诚劳务服务有限公司 | D8: PO260831L | E8: SR260831L | F8: 46265 | G8: 904000 | H8: =MAX(0,DATE(2026,8,31)-F8) -> 0 | J8: HR | K8: 未开始
A9: GRNI-004 | G9: 0
A10: GRNI-005 | G10: 0
A11: GRNI-006 | G11: 0
A12: GRNI-007 | G12: 0
A13: GRNI-008 | G13: 0
A14: GRNI-009 | G14: 0
A15: GRNI-010 | G15: 0
A16: GRNI-011 | G16: 0
A17: GRNI-012 | G17: 0
A18: GRNI-013 | G18: 0
A19: GRNI-014 | G19: 0
A20: GRNI-015 | G20: 0
... A45: GRNI-040 | G45: 0

Sheet 04-三单匹配
A1: PO—收货/验收—发票匹配
A2: 容差是分流规则，不替代真实性判断。
A5: 匹配ID | B5: 应付ID | C5: 供应商 | D5: PO | E5: 收货/验收 | F5: 发票 | G5: PO金额 | H5: 收货金额 | I5: 发票金额 | J5: 匹配结果 | K5: 是否争议 | L5: Owner | M5: 差异处理
A6: MAT-001 | B6: AP001 | C6: 芯联电子科技有限公司 | D6: PO260701 | E6: GR260701 | F6: INV260710 | G6: 2260000 | H6: 2260000 | I6: 2260000 | J6: 已匹配 | K6: 否 | L6: 采购一部
A7: MAT-002 | B7: AP002 | C7: 芯联电子科技有限公司 | D7: PO260818 | E7: GR260818 | G7: 1695000 | H7: 1695000 | I7: 1695000 | J7: 缺发票 | K7: 否 | L7: 采购一部
A8: MAT-003 | B8: AP003 | C8: 东莞精工金属有限公司 | D8: PO260620 | E8: GR260620 | F8: INV260625 | G8: 1356000 | H8: 1356000 | I8: 1356000 | J8: 已匹配 | K8: 否 | L8: 采购一部
A9: MAT-004 | B9: AP004 | C9: 华南塑胶科技有限公司 | D9: PO260510 | E9: GR260510 | F9: INV260515 | G9: 904000 | H9: 904000 | I9: 904000 | J9: 已匹配 | K9: 是 | L9: 采购二部
A10: MAT-005 | B10: AP005 | C10: 云启软件服务有限公司 | D10: PO260801 | E10: SR260801 | F10: INV260801 | G10: 678000 | H10: 678000 | I10: 678000 | J10: 已匹配 | K10: 否 | L10: IT
A11: MAT-006 | B11: AP006 | C11: 迅捷物流有限公司 | D11: PO260731 | E11: SR260731 | F11: INV260805 | G11: 339000 | H11: 339000 | I11: 339000 | J11: 已匹配 | K11: 否 | L11: 物流部
A12: MAT-007 | B12: AP007 | C12: 德信咨询有限公司 | D12: PO260715 | F12: INV260720 | G12: 565000 | H12: 565000 | I12: 565000 | J12: 已匹配 | K12: 是 | L12: 总经办
A13: MAT-008 | B13: AP008 | C13: 力源设备股份有限公司 | D13: PO260501 | E13: FA260812 | F13: INV260812 | G13: 2260000 | H13: 2260000 | I13: 2260000 | J13: 已匹配 | K13: 否 | L13: 设备部
A14: MAT-009 | B14: AP009 | C14: 华南包装有限公司 | D14: PO260825 | E14: GR260825 | F14: INV260827 | G14: 452000 | H14: 452000 | I14: 452000 | J14: 已匹配 | K14: 否 | L14: 采购二部
A15: MAT-010 | B15: AP010 | C15: 绿能电力服务有限公司 | D15: PO260831 | E15: SR260831 | G15: 791000 | H15: 791000 | I15: 791000 | J15: 缺发票 | K15: 否 | L15: 行政部
A16: MAT-011 | B16: AP011 | C16: 瑞诚劳务服务有限公司 | D16: PO260731L | E16: SR260731L | F16: INV260805L | G16: 1130000 | H16: 1130000 | I16: 1130000 | J16: 已匹配 | K16: 否 | L16: HR
A17: MAT-012 | B17: AP012 | C17: 宏达贸易有限公司 | D17: PO260810 | E17: GR260810 | F17: INV260812M | G17: 226000 | H17: 226000 | I17: 226000 | J17: 已匹配 | K17: 是 | L17: 采购二部
A18: MAT-013 | B18: AP013 | C18: 华辰供应链有限公司 | D18: PO260630 | E18: GR260630 | F18: INV260705 | G18: 1808000 | H18: 1808000 | I18: 1808000 | J18: 已匹配 | K18: 否 | L18: 供应链
A19: MAT-014 | B19: AP014 | C19: 东莞精工金属有限公司 | D19: PO250215 | E19: GR250215 | F19: INV250220 | G19: 113000 | H19: 113000 | I19: 113000 | J19: 已匹配 | K19: 否 | L19: 采购一部
A20: MAT-015 | B20: AP015 | C20: 华南塑胶科技有限公司 | D20: PO260829 | E20: GR260829 | F20: INV260830 | G20: 339000 | H20: 339000 | I20: 339000 | J20: 已匹配 | K20: 是 | L20: 采购二部
A21: MAT-016 | B21: AP016 | C21: 华南包装有限公司 | D21: PO260830 | E21: GR260830 | F21: INV260831 | G21: 226000 | H21: 226000 | I21: 226000 | J21: 已匹配 | K21: 否 | L21: 采购二部
A22: MAT-017 | B22: AP017 | C22: 迅捷物流有限公司 | D22: PO260820 | E22: SR260820 | F22: INV260825 | G22: 169500 | H22: 169500 | I22: 169500 | J22: 已匹配 | K22: 否 | L22: 物流部
A23: MAT-018 | B23: AP018 | C23: 瑞诚劳务服务有限公司 | D23: PO260831L | E23: SR260831L | G23: 904000 | H23: 904000 | I23: 904000 | J23: 缺发票 | K23: 否 | L23: HR

Sheet 05-付款计划
A1: 未来13周付款计划
A2: 付款优先级同时考虑到期、关键供应、争议、折扣、合规和现金。
A5: 计划ID | B5: 应付ID | C5: 供应商 | D5: 到期日 | E5: 余额 | F5: 业务状态 | G5: 争议 | H5: 责任部门 | I5: 优先级/理由 | J5: 计划付款日 | K5: 状态
A6: PAY-001 | B6: AP001 | C6: 芯联电子科技有限公司 | D6: 46266 | E6: 2260000 | F6: 待付款 | G6: 否 | H6: 采购一部 | K6: 待排程
A7: PAY-002 | B7: AP002 | C7: 芯联电子科技有限公司 | D7: 46312 | E7: 1695000 | F7: 暂估未到票 | G7: 否 | H7: 采购一部 | K7: 待排程
A8: PAY-003 | B8: AP003 | C8: 东莞精工金属有限公司 | D8: 46238 | E8: 856000 | F8: 逾期 | G8: 否 | H8: 采购一部 | K8: 待排程
A9: PAY-004 | B9: AP004 | C9: 华南塑胶科技有限公司 | D9: 46182 | E9: 904000 | F9: 冻结争议 | G9: 是 | H9: 采购二部 | K9: 待排程
A10: PAY-005 | B10: AP006 | C10: 迅捷物流有限公司 | D10: 46264 | E10: 339000 | F10: 逾期 | G10: 否 | H10: 物流部 | K10: 待排程
A11: PAY-006 | B11: AP007 | C11: 德信咨询有限公司 | D11: 46248 | E11: 565000 | F11: 发票先到未验收 | G11: 是 | H11: 总经办 | K11: 待排程
A12: PAY-007 | B12: AP008 | C12: 力源设备股份有限公司 | D12: 46276 | E12: 1130000 | F12: 设备尾款 | G12: 否 | H12: 设备部 | K12: 待排程
A13: PAY-008 | B13: AP009 | C13: 华南包装有限公司 | D13: 46304 | E13: 452000 | F13: 待付款 | G13: 否 | H13: 采购二部 | K13: 待排程
A14: PAY-009 | B14: AP010 | C14: 绿能电力服务有限公司 | D14: 46280 | E14: 791000 | F14: 暂估未到票 | G14: 否 | H14: 行政部 | K14: 待排程
A15: PAY-010 | B15: AP011 | C15: 瑞诚劳务服务有限公司 | D15: 46264 | E15: 1130000 | F15: 逾期 | G15: 否 | H15: HR | K15: 待排程
A16: PAY-011 | B16: AP012 | C16: 宏达贸易有限公司 | D16: 46274 | E16: 226000 | F16: 付款冻结 | G16: 是 | H16: 采购二部 | K16: 待排程
A17: PAY-012 | B17: AP013 | C17: 华辰供应链有限公司 | D17: 46263 | E17: 1008000 | F17: 逾期关联方 | G17: 否 | H17: 供应链 | K17: 待排程
... A21: PAY-016 | B21: AP018 | C21: 瑞诚劳务服务有限公司 | D21: 46295 | E21: 904000 | F21: 暂估未到票 | G21: 否 | H21: HR | K21: 待排程
A22: PAY-017 | E22: 0
A23: PAY-018 | E23: 0
A24: PAY-019 | E24: 0
A25: PAY-020 | E25: 0
A26: PAY-021 | E26: 0
A27: PAY-022 | E27: 0
A28: PAY-023 | E28: 0
A29: PAY-024 | E29: 0
A30: PAY-025 | E30: 0
A31: PAY-026 | E31: 0
A32: PAY-027 | E32: 0
A33: PAY-028 | E33: 0
... A63: PAY-058 | E63: 0

Sheet 06-付款审批
A1: 付款审批与执行
A2: 制单、复核、授权和银行执行应适当分离。
A5: 申请号 | B5: 供应商 | C5: 应付ID | D5: 付款事由 | E5: 金额 | F5: 到期/例外依据 | G5: 匹配状态 | H5: 收款账户 | I5: 账户变更标识 | J5: 申请人 | K5: 审批状态 | L5: 网银流水 | M5: 退汇/退款
A6: PA-001 | E6: 0 | K6: 待审批
A7: PA-002 | E7: 0 | K7: 待审批
A8: PA-003 | E8: 0 | K8: 待审批
A9: PA-004 | E9: 0 | K9: 待审批
A10: PA-005 | E10: 0 | K10: 待审批
A11: PA-006 | E11: 0 | K11: 待审批
A12: PA-007 | E12: 0 | K12: 待审批
A13: PA-008 | E13: 0 | K13: 待审批
A14: PA-009 | E14: 0 | K14: 待审批
A15: PA-010 | E15: 0 | K15: 待审批
A16: PA-011 | E16: 0 | K16: 待审批
A17: PA-012 | E17: 0 | K17: 待审批
... A55: PA-050 | E55: 0 | K55: 待审批

Sheet 07-账户变更
A1: 供应商银行账户变更
A2: 禁止仅按变更邮件内的联系方式核验。
A5: 变更ID | B5: 供应商编码 | C5: 供应商 | D5: 原账户 | E5: 新账户 | F5: 申请日期 | G5: 申请渠道 | H5: 独立回拨 | I5: 复核人 | J5: 状态 | K5: 批准日 | L5: 临时控制
A6: BC-001 | B6: S011 | C6: 宏达贸易有限公司 | D6: 6222****7180 | E6: 个人账户6222****9918 | F6: 2026-08-28 | G6: 邮件 | H6: 未完成 | I6: 资金主管 | J6: 待核验 | L6: 冻结付款
A7: BC-002
A8: BC-003
A9: BC-004
A10: BC-005
A11: BC-006
A12: BC-007
A13: BC-008
A14: BC-009
A15: BC-010
A16: BC-011
A17: BC-012
A18: BC-013
... A45: BC-040

Sheet 08-供应商对账
A1: 供应商余额对账
A2: 差异不能只写“时间差”，必须定位单据和关闭动作。
A5: 对账ID | B5: 编码 | C5: 供应商 | D5: 账面余额 | E5: 对账单余额 | F5: 差异 | G5: 差异类型 | H5: 处理动作 | I5: 责任部门 | J5: 状态 | K5: Closure证据
A6: REC-001 | B6: S001 | C6: 芯联电子科技有限公司 | D6: 0 | E6: 0 | F6: 0 | I6: 采购一部 | J6: 未开始
A7: REC-002 | B7: S002 | C7: 东莞精工金属有限公司 | D7: 0 | E7: 0 | F7: 0 | I7: 采购一部 | J7: 未开始
A8: REC-003 | B8: S003 | C8: 华南塑胶科技有限公司 | D8: 0 | E8: 0 | F8: 0 | I8: 采购二部 | J8: 未开始
A9: REC-004 | B9: S004 | C9: 云启软件服务有限公司 | D9: 0 | E9: 0 | F9: 0 | I9: IT | J9: 未开始
A10: REC-005 | B10: S005 | C10: 迅捷物流有限公司 | D10: 0 | E10: 0 | F10: 0 | I10: 物流部 | J10: 未开始
A11: REC-006 | B11: S006 | C11: 德信咨询有限公司 | D11: 0 | E11: 0 | F11: 0 | I11: 总经办 | J11: 未开始
A12: REC-007 | B12: S007 | C12: 力源设备股份有限公司 | D12: 0 | E12: 0 | F12: 0 | I12: 设备部 | J12: 未开始
A13: REC-008 | B13: S008 | C13: 华南包装有限公司 | D13: 0 | E13: 0 | F13: 0 | I13: 采购二部 | J13: 未开始
A14: REC-009 | B14: S009 | C14: 绿能电力服务有限公司 | D14: 0 | E14: 0 | F14: 0 | I14: 行政部 | J14: 未开始
A15: REC-010 | B15: S010 | C15: 瑞诚劳务服务有限公司 | D15: 0 | E15: 0 | F15: 0 | I15: HR | J15: 未开始
A16: REC-011 | B16: S011 | C16: 宏达贸易有限公司 | D16: 0 | E16: 0 | F16: 0 | I16: 采购二部 | J16: 未开始
A17: REC-012 | B17: S012 | C17: 华辰供应链有限公司 | D17: 0 | E17: 0 | F17: 0 | I17: 供应链 | J17: 未开始

Sheet 09-争议索赔
A1: 供应商争议与索赔
A2: 无争议部分和争议部分分开管理。
A5: 争议ID | B5: 应付ID | C5: 供应商 | D5: 争议金额 | E5: 事项 | F5: 供应商主张 | G5: 公司判断 | H5: 合同依据 | I5: Owner | J5: 下一步 | K5: 截止日 | L5: 状态 | M5: 会计/付款影响
A6: DIS-001 | B6: AP004 | C6: 华南塑胶科技有限公司 | D6: 904000 | E6: 质量扣款90,400待确认 | I6: 采购二部 | L6: Open
A7: DIS-002 | B7: AP007 | C7: 德信咨询有限公司 | D7: 565000 | E7: 成果报告未验收 | I7: 总经办 | L7: Open
A8: DIS-003 | B8: AP012 | C8: 宏达贸易有限公司 | D8: 226000 | E8: 邮件要求改付个人账户 | I8: 采购二部 | L8: Open
A9: DIS-004 | B9: AP015 | C9: 华南塑胶科技有限公司 | D9: -61000 | E9: 付款超过本发票，需查预付或串户 | I9: 采购二部 | L9: Open
A10: DIS-004 | D10: 0
A11: DIS-005 | D11: 0
A12: DIS-006 | D12: 0
A13: DIS-007 | D13: 0
A14: DIS-008 | D14: 0
A15: DIS-009 | D15: 0
A16: DIS-010 | D16: 0
A17: DIS-011 | D17: 0
A18: DIS-012 | D18: 0
A19: DIS-013 | D19: 0
A20: DIS-014 | D20: 0
A21: DIS-015 | D21: 0
... A46: DIS-040 | D46: 0

Sheet 10-预付跟踪
A1: 预付款与履约跟踪
A2: 预付后必须跟踪交付、里程碑、担保和退款权。
A5: 预付ID | B5: 编码 | C5: 供应商 | D5: 合同/PO | E5: 余额 | F5: 预付日 | G5: 约定交付日 | H5: 履约状态 | I5: Owner | J5: 状态 | K5: 处理
A6: ADV-001 | B6: S004 | C6: 云启软件服务有限公司 | D6: PO260801 | E6: 678000 | F6: 46235 | G6: 46235 | H6: SaaS已开通，按期摊销 | I6: IT | J6: 正常
A7: ADV-002 | B7: S007 | C7: 力源设备股份有限公司 | D7: PO260501 | E7: 1130000 | F7: 46143 | G7: 46246 | H7: 设备已验收，转入设备结算 | I7: 设备部 | J7: 正常
A8: ADV-003 | B8: S011 | C8: 宏达贸易有限公司 | D8: PO260601 | E8: 300000 | F8: 46174 | G8: 46218 | H8: 供应商账户异常，未交货 | I8: 采购二部 | J8: 逾期 | K8: 冻结新增预付并追款
A9: ADV-004 | E9: 0
A10: ADV-005 | E10: 0
A11: ADV-006 | E11: 0
A12: ADV-007 | E12: 0
A13: ADV-008 | E13: 0
A14: ADV-009 | E14: 0
A15: ADV-010 | E15: 0
A16: ADV-011 | E16: 0
A17: ADV-012 | E17: 0
A18: ADV-013 | E18: 0
A19: ADV-014 | E19: 0
A20: ADV-015 | E20: 0
... A45: ADV-040 | E45: 0

Sheet 11-核心指标
A1: 应付与供应商核心指标
A2: 指标是下钻入口，不是最终结论。
A5: 指标 | B5: 定义 | C5: 管理意义 | D5: 恶化原因 | E5: 下钻方向
A6: 应付余额 | B6: 期末应付未清项合计 | C6: 衡量无息经营融资与到期义务 | D6: 余额下降可能是采购下降、提前付款或漏记；上升可能是采购增长、延付或暂估积压 | E6: 按供应商、采购类别、到期状态、暂估/已票、关联方下钻
A7: 逾期应付率 | B7: 逾期余额÷应付余额 | C7: 反映履约、信用与供应连续性 | D7: 现金短缺、流程堵塞、争议未闭环、付款计划失真 | E7: 先分无争议逾期与争议，再看Owner和付款承诺
A8: 未来30天到期额 | B8: 未来30天到期的应付余额 | C8: 连接付款排程与滚动现金预测 | D8: 集中采购、账期缩短或历史延期集中到期 | E8: 按日、供应商重要性和资金缺口下钻
A9: 暂估未到票余额/账龄 | B9: 已收货验收但未取得发票的估计负债 | C9: 检查负债完整性、成本截止和税务资料 | D9: 供应商开票慢、收货单未关、暂估未冲或虚假暂估 | E9: 按PO/GR、责任采购、30/60/90天、金额差异下钻
A10: 三单匹配例外率 | B10: PO/收货验收/发票不一致项目数或金额占比 | C10: 反映采购执行和付款风险 | D10: 数量、价格、税率、主体、收货或重复票异常 | E10: 按例外类型、采购员、供应商和容差原因下钻
A11: 提前付款比例 | B11: 未到期即付款金额÷总付款额 | C11: 衡量资金占用和审批纪律 | D11: 供应商强势、折扣有利、资金计划失控或关联方倾斜 | E11: 核对折扣收益、批准依据和实际交付
A12: 预付账款周转/逾期预付 | B12: 预付后长期未收货或未结算的金额 | C12: 识别履约和资金风险 | D12: 供应商延期、项目取消、验收滞后或舞弊 | E12: 按合同里程碑、担保、责任人和追偿状态下钻
A13: 供应商集中度 | B13: 前五大供应商采购额/总采购额 | C13: 衡量供应连续性与议价风险 | D13: 单一来源、技术锁定、关联交易或采购策略变化 | E13: 结合替代周期、库存保障、财务健康和质量表现
A14: 重复付款/退款未收回 | B14: 重复支付或应收供应商退款余额 | C14: 直接反映资金损失与控制失效 | D14: 重复发票、拆票、主数据重复、核销错误 | E14: 查发票号、金额、银行账户、付款批次和审批日志

Sheet 12-月末Checklist
A1: 应付月末检查清单
A2: 每项必须有执行证据、复核和关闭标准。
A5: 明确动作 | B5: 责任人 | C5: 期限 | D5: 证据 | E5: 关闭标准 | F5: 完成状态 | G5: 复核人 | H5: 复核日
A6: 冻结本月应付子模块期间，确认最后收货、发票和付款批次已完成 | B6: AP主管 | C6: D+1 | D6: 关闭通知、系统期间截图 | E6: 禁止未授权回写 | F6: 未开始
A7: 取得采购在途、已收货未入账、服务已验收未开票清单并完成截止性测试 | B7: 总账/AP | C7: D+2 | D7: PO、GR、验收、暂估底稿 | E7: 所有重大负债均记录 | F7: 未开始
A8: 逐项复核暂估新增、冲销和60天以上未到票，并确定Owner及期限 | B8: 财务主管 | C8: D+3 | D8: GRNI账龄、采购回复 | E8: 长期项进入Issue Log | F8: 未开始
A9: 完成AP明细与总账、供应商对账单及付款后事项核对 | B9: AP | C9: D+3 | D9: 对账底稿、差异说明 | E9: 差异为零或获批未决 | F9: 未开始
A10: 扫描应付负余额、借方余额、无供应商明细、非贸易项目及关联方余额 | B10: 总账 | C10: D+3 | D10: 异常余额清单 | E10: 按实质调账或重分类 | F10: 未开始
A11: 核对进项发票、入账、用途和抵扣管理，识别不得抵扣或待转出事项 | B11: 税务/AP | C11: D+4 | D11: 发票平台及税务台账 | E11: 账票用途一致 | F11: 未开始
A12: 更新未来13周付款预测，区分法定/合同到期、关键供应、折扣和争议款 | B12: 资金/AP | C12: D+4 | D12: 付款计划、现金预测 | E12: 资金缺口已升级 | F12: 未开始
A13: 复核大额、异常账户变更、第三方付款、拆分付款和重复支付预警 | B13: 财务主管 | C13: D+4 | D13: 审批链和银行回单 | E13: 异常均有独立验证 | F13: 未开始
A14: 形成Top供应商、逾期、GRNI、争议、预付和Issue管理报告 | B14: 财务主管 | C14: D+5 | D14: 月度管理包 | E14: Owner、日期、金额和Closure明确 | F14: 未开始

Sheet 13-接手检查
A1: 新财务主管接手检查
A2: 记录资料、事实、临时控制和历史责任边界。
A5: 阶段 | B5: 事项 | C5: 检查动作 | D5: 发现/证据 | E5: 状态
A6: 第一周 | B6: 供应商主数据和权限 | C6: 导出主数据、银行变更日志和权限矩阵 | E6: 未开始
A7: 第一周 | B7: AP与GL | C7: 重做子模块总账对账 | E7: 未开始
A8: 第一周 | B8: GRNI | C8: 扫描60/90天以上暂估 | E8: 未开始
A9: 第一周 | B9: 负余额和预付 | C9: 穿透银行及未清项 | E9: 未开始
A10: 第一月 | B10: 付款批次 | C10: 抽查大额、账户变更、第三方和退汇 | E10: 未开始
A11: 第一月 | B11: 供应商真实性 | C11: 抽查同账户、关联关系和休眠重启 | E11: 未开始
A12: 第一月 | B12: 逾期与中小企业款项 | C12: 区分无争议到期与争议 | E12: 未开始
A13: 第一月 | B13: 历史Issue边界 | C13: 形成基准日问题清单并书面汇报 | E13: 未开始

Sheet 14-风险红旗
A1: 采购付款风险红旗
A2: 发现红旗后先控制风险，再核实和升级。
A5: 控制 | B5: 风险 | C5: 控制动作 | D5: 证据
A6: 主数据创建与付款分离 | B6: 采购员创建供应商并可改银行账户、发起付款 | C6: 供应商创建、银行变更、发票处理和付款权限分离；定期复核日志 | D6: 主数据审批、变更日志、权限矩阵
A7: 银行账户独立回拨验证 | B7: 仅凭邮件更换收款账户 | C7: 使用合同留存联系人或公开电话独立确认，禁止按变更邮件内号码验证 | D7: 回拨记录、录音/邮件、双人复核
A8: 三单匹配与容差审批 | B8: 无PO、无收货或价格数量差异仍付款 | C8: 系统匹配PO、收货/验收与发票；超容差由采购和业务批准 | D8: 匹配报告、例外审批
A9: 重复发票和付款控制 | B9: 同票不同格式、拆分或跨主体重复支付 | C9: 按发票号码、销方税号、金额、日期及银行账号组合查重 | D9: 重复检测日志、退款跟踪
A10: 付款批次职责分离 | B10: 制单人可审批并网银放款 | C10: 制单、复核、授权和银行U盾分离；批次总额与明细核对 | D10: 付款申请、网银日志
A11: 截止性与暂估控制 | B11: 用到票时间代替收货验收时间确认负债 | C11: 月末从GR、在途、服务验收和后续发票反向检查 | D11: 截止测试、GRNI清单
A12: 供应商利益冲突声明 | B12: 员工或关联方隐瞒关系 | C12: 准入阶段收集受益所有人和员工关系声明，定期更新 | D12: 尽调、关联方清单
A13: 付款优先级透明 | B13: 现金紧张时按个人关系插队 | C13: 书面规则综合法定到期、生产连续性、违约成本和折扣收益；例外审批 | D13: 付款排序表、例外审批

Sheet 15-Issue Log
A1: 应付Issue与Closure
A2: Resolved后仍需验证账务、付款、主数据和流程整改。
A5: Issue | B5: 供应商 | C5: 问题 | D5: 来源 | E5: 金额 | F5: 影响 | G5: Owner | H5: 下一步 | I5: 截止日 | J5: 临时控制 | K5: 会计处理 | L5: 管理整改 | M5: 复核人 | N5: 状态 | O5: Closure证据
A6: ISS-001 | B6: 宏达贸易 | C6: 改付个人账户且供应商已冻结 | D6: 付款前检查 | E6: 226000 | F6: 资金损失/欺诈 | G6: 资金主管 | H6: 原联系人独立核验并取得合法文件 | I6: 46277 | J6: 冻结付款和账户变更 | K6: 保持应付未清 | L6: 完善回拨控制 | M6: 财务经理 | N6: Open
A7: ISS-002 | B7: 华南塑胶 | C7: 应付负余额61,000及质量争议 | D7: 月结 | E7: 61000 | F7: 列报/资金/争议 | G7: AP主管 | H7: 穿透付款、退货和串户 | I7: 46280 | J7: 禁止跨供应商冲抵 | K7: 待事实确认后调账 | L7: 建立负余额月度扫描 | M7: 财务主管 | N7: Open
A8: ISS-003 | B8: 东莞精工 | C8: 113,000元挂账18个月 | D8: 供应商对账 | E8: 113000 | F8: 错账/历史舞弊 | G8: AP主管 | H8: 核对银行、批次和对账单 | I8: 46285 | J8: 暂停核销 | K8: 证据充分后更正 | L8: 年度函证与账龄清理 | M8: 财务主管 | N8: In Progress
A9: ISS-004 | E9: 0
A10: ISS-005 | E10: 0
A11: ISS-006 | E11: 0
A12: ISS-007 | E12: 0
A13: ISS-008 | E13: 0
A14: ISS-009 | E14: 0
A15: ISS-010 | E15: 0
A16: ISS-011 | E16: 0
A17: ISS-012 | E17: 0
A18: ISS-013 | E18: 0
A19: ISS-014 | E19: 0
A20: ISS-015 | E20: 0
... A65: ISS-060 | E65: 0

Sheet 16-RACI
A1: 岗位责任矩阵
A2: 业务负责需求和履约事实，财务负责数据、支付控制、核算和监督。
A5: 事项 | B5: 执行 | C5: 财务主管 | D5: 协同 | E5: 批准
A6: 供应商需求与采购策略 | B6: 采购负责人 | C6: 监控流程和关键风险 | D6: 需求部门/法务 | E6: 采购总监
A7: 供应商准入与尽调 | B7: 采购/主数据管理员 | C7: 复核财税与关联方字段 | D7: 法务/质量/合规 | E7: 采购总监
A8: 采购订单与合同 | B8: 采购 | C8: 检查付款、税价和结算条款 | D8: 需求部门/法务 | E8: 授权审批人
A9: 收货和验收 | B9: 仓库/需求部门 | C9: 监督未验收长期挂账 | D9: 质量/采购 | E9: 业务负责人
A10: 发票接收和三单匹配 | B10: AP会计 | C10: 复核例外、容差和截止性 | D10: 采购/仓库/税务 | E10: 财务主管
A11: 暂估和冲销 | B11: AP/成本会计 | C11: 复核完整性、账龄和差异 | D11: 仓库/采购 | E11: 财务主管
A12: 付款计划 | B12: AP/资金 | C12: 决定财务排序并揭示到期风险 | D12: 采购/业务 | E12: 财务经理
A13: 付款执行 | B13: 资金/出纳 | C13: 复核审批、账户和防重复 | D13: AP/采购 | E13: 授权审批人
A14: 供应商对账 | B14: AP/采购 | C14: 复核重大差异及Closure | D14: 供应商/仓库 | E14: 财务主管
A15: 争议与索赔 | B15: 采购/业务 | C15: 评估账务、现金及披露影响 | D15: 法务/质量 | E15: 业务负责人
A16: 供应商绩效和退出 | B16: 采购 | C16: 提供付款与异常数据 | D16: 质量/业务 | E16: 采购总监

Sheet 17-案例库
A1: 应付及供应商管理案例
A2: 可用于面试、入职和月度复盘。
A5: 编号 | B5: 场景 | C5: 第一步 | D5: 沟通对象 | E5: 处理方案 | F5: 升级条件 | G5: 我的回答
A6: AP-001 | B6: 原材料已入库113万元，月末未收到发票 | C6: 以收货和控制权事实确认负债，按不含可抵扣税的合理金额暂估；通常不暂估进项税 | D6: 采购/仓库/成本 | E6: 次月发票到达后冲暂估并按实际发票入账，分析价差 | F6: 60天仍未到票或金额重大
A7: AP-002 | B7: 发票已到但货物尚未到达 | C7: 先查控制权和贸易条款，不能见票即确认存货/成本 | D7: 采购/物流 | E7: 可在发票工作流挂起；若控制权已转移则结合在途物资处理 | F7: 供应商要求立即付款且无履约保障
A8: AP-003 | B8: 发票数量1000件，仓库只收980件 | C8: 冻结差异部分，确认是短装、在途、收货错误还是发票错误 | D8: 仓库/采购/供应商 | E8: 无争议部分按企业政策处理，差异部分退票、补货或索赔 | F8: 采购要求财务全额付款
A9: AP-004 | B9: 应付账款出现61,000元借方余额 | C9: 穿透未清项，判断预付、超付、退货退款、串户或错账，不机械重分类 | D9: AP/资金/采购 | E9: 按真实实质转预付、其他应收、跨供应商更正或追回 | F9: 供应商否认余额或长期不清
A10: AP-005 | B10: 发票入账后发生采购退货 | C10: 取得退货出库、供应商确认和红字发票资料 | D10: 仓库/采购/税务 | E10: 冲减存货/成本和应付，按增值税规定处理进项扣减 | F10: 货已退但红票长期未办
A11: AP-006 | B11: 供应商邮件通知收款账户改为个人账户 | C11: 立即冻结付款，使用原留存联系人独立回拨核验 | D11: 采购/法务/供应商 | E11: 未经批准和充分证明不得改主数据或付款 | F11: 疑似邮箱入侵、账户主体不一致
A12: AP-007 | B12: 生产急料未走PO，要求当天付款 | C12: 先保证业务事实和授权，建立紧急采购例外而非事后补假资料 | D12: 生产/采购 | E12: 限额、两级审批、事后补齐及月度复盘；重复发生要改流程 | F12: 规避招标、关联方或大额拆分
A13: AP-008 | B13: 同一电子发票被两个报账人提交 | C13: 冻结第二笔并检查是否已付款、是否跨主体重复 | D13: AP/申请人 | E13: 系统以销方税号+发票号+金额查重，错误入账及时冲销 | F13: 已重复支付且供应商不退款
A14: AP-009 | B14: 账上113,000元挂账18个月，供应商称早已收款 | C14: 核对银行流水、付款批次、供应商对账和核销记录 | D14: 资金/AP/供应商 | E14: 找到错核销或串户后调账；无法证实不得直接转营业外收入 | F14: 可能存在账外支付或历史舞弊
A15: AP-010 | B15: 质量问题拟扣供应商90,400元 | C15: 确认合同索赔权、质量证据和供应商接受程度 | D15: 质量/采购/法务 | E15: 无争议部分及时付款，争议金额单独跟踪；会计处理取决于事实和可执行性 | F15: 长期以质量名义拖欠全部款项
A16: AP-011 | B16: 应付中挂有员工报销、借款和押金 | C16: 识别对手方及经济实质，不能只因未来要付款就放应付账款 | D16: 总账/费用/资金 | E16: 分别转其他应付款、短期借款或其他适当科目 | F16: 重分类掩盖关联方或融资
A17: AP-012 | B17: 供应商要求支付给其指定的第三方 | C17: 核实合法依据、三方协议、债权转让或代收关系及税务资料 | D17: 采购/法务/税务 | E17: 获得完整授权和独立验证后按审批支付并保留闭环证据 | F17: 资金去向异常或对公转个人
... A23: AP-018 | B23: 供应商预付款后连续90天未交货 | C23: 核对合同里程碑、担保、履约进度和退款权 | D23: 采购/法务/项目 | E23: 冻结新增预付，要求履约、担保或退款并评估减值迹象 | F23: 供应商失联或经营异常

Sheet 18-资料来源
A1: 法规、税务与内控资料
A2: 实际处理时重新核对业务发生时有效规定。
A5: 名称 | B5: 文件号 | C5: 关系 | D5: 官方网址
A6: 企业内部控制应用指引第7号——采购业务 | B6: 财会〔2010〕11号配套指引 | C6: 请购、审批、购买、验收、付款和采购后评估的风险控制 | D6: https://kjs.mof.gov.cn/zhengcefabu/201005/P020230421440664863663.pdf
A7: 企业所得税税前扣除凭证管理办法 | B7: 国家税务总局公告2018年第28号 | C7: 税前扣除凭证真实性、合法性、关联性及补救规则 | D7: https://fgk.chinatax.gov.cn/zcfgk/c100012/c5194804/content.html
A8: 保障中小企业款项支付条例 | B8: 国务院令第802号 | C8: 2025-06-01施行；大型企业付款期限、无争议款、逾期利息及公示等 | D8: https://www.miit.gov.cn/jgsj/zfs/xzfg/art/2025/art_d9b6cd05f3734869aa34caff247089ff.html
A9: 中华人民共和国增值税法 | B9: 主席令第四十一号 | C9: 2026-01-01施行；进项税额与不得抵扣项目等法定框架 | D9: https://www.npc.gov.cn/npc/c2/c30834/202412/t20241225_442015.html
A10: 中华人民共和国增值税法实施条例 | B10: 国务院令第826号 | C10: 2026-01-01施行；进项用途、混合用途及转出等细化规则 | D10: https://tianjin.chinatax.gov.cn/11200000000/0300/030004/03000418/20251231101843846.shtml
A11: 中华人民共和国会计法（2024年修正） | B11: 2024-07-01施行 | C11: 真实完整会计资料、内部监督和会计信息化 | D11: https://www.mof.gov.cn/zhengwuxinxi/caizhengxinwen/202406/t20240629_3938355.htm
